BeginnersbookJavaIoJiaochengChuyi/README.md
BeginnersbookJavaIoJiaochengChuyi/__init__.py
BeginnersbookJavaIoJiaochengChuyi/__main__.py
BeginnersbookJavaIoJiaochengChuyi/file.epub
BeginnersbookJavaIoJiaochengChuyi/index.html
BeginnersbookJavaIoJiaochengChuyi/css/__init__.py
BeginnersbookJavaIoJiaochengChuyi/css/annotations.css
BeginnersbookJavaIoJiaochengChuyi/css/main.css
BeginnersbookJavaIoJiaochengChuyi/css/normalize.css
BeginnersbookJavaIoJiaochengChuyi/css/popup.css
BeginnersbookJavaIoJiaochengChuyi/font/__init__.py
BeginnersbookJavaIoJiaochengChuyi/font/fontello.eot
BeginnersbookJavaIoJiaochengChuyi/font/fontello.svg
BeginnersbookJavaIoJiaochengChuyi/font/fontello.ttf
BeginnersbookJavaIoJiaochengChuyi/font/fontello.woff
BeginnersbookJavaIoJiaochengChuyi/img/__init__.py
BeginnersbookJavaIoJiaochengChuyi/img/annotator-glyph-sprite.png
BeginnersbookJavaIoJiaochengChuyi/img/annotator-icon-sprite.png
BeginnersbookJavaIoJiaochengChuyi/img/apple-touch-icon.png
BeginnersbookJavaIoJiaochengChuyi/img/cancelfullscreen.png
BeginnersbookJavaIoJiaochengChuyi/img/close.png
BeginnersbookJavaIoJiaochengChuyi/img/fullscreen.png
BeginnersbookJavaIoJiaochengChuyi/img/loader.gif
BeginnersbookJavaIoJiaochengChuyi/img/menu-icon.png
BeginnersbookJavaIoJiaochengChuyi/img/save.png
BeginnersbookJavaIoJiaochengChuyi/img/saved.png
BeginnersbookJavaIoJiaochengChuyi/img/settings-s.png
BeginnersbookJavaIoJiaochengChuyi/img/settings.png
BeginnersbookJavaIoJiaochengChuyi/img/star.png
BeginnersbookJavaIoJiaochengChuyi/js/__init__.py
BeginnersbookJavaIoJiaochengChuyi/js/epub.js
BeginnersbookJavaIoJiaochengChuyi/js/epub.min.js
BeginnersbookJavaIoJiaochengChuyi/js/epub.min.map
BeginnersbookJavaIoJiaochengChuyi/js/hooks.min.js
BeginnersbookJavaIoJiaochengChuyi/js/hooks.min.map
BeginnersbookJavaIoJiaochengChuyi/js/reader.js
BeginnersbookJavaIoJiaochengChuyi/js/reader.js.map
BeginnersbookJavaIoJiaochengChuyi/js/reader.min.js
BeginnersbookJavaIoJiaochengChuyi/js/reader.min.map
beginnersbook_java_io_jiaocheng_chuyi-2024.3.4.0.dist-info/METADATA
beginnersbook_java_io_jiaocheng_chuyi-2024.3.4.0.dist-info/WHEEL
beginnersbook_java_io_jiaocheng_chuyi-2024.3.4.0.dist-info/entry_points.txt
beginnersbook_java_io_jiaocheng_chuyi-2024.3.4.0.dist-info/top_level.txt
beginnersbook_java_io_jiaocheng_chuyi-2024.3.4.0.dist-info/RECORD
